README.md
setup.cfg
setup.py
agario_bot/__init__.py
agario_bot/bot.py
agario_bot.egg-info/PKG-INFO
agario_bot.egg-info/SOURCES.txt
agario_bot.egg-info/dependency_links.txt
agario_bot.egg-info/requires.txt
agario_bot.egg-info/top_level.txt